<?xml version="1.0" encoding="utf-8"?>
<savedqueries>
  <savedquery>
    <IsCustomizable>1</IsCustomizable>
    <CanBeDeleted>1</CanBeDeleted>
    <isquickfindquery>0</isquickfindquery>
    <isprivate>0</isprivate>
    <isdefault>0</isdefault>
    <savedqueryid>{d1f6d192-d143-e811-a95b-000d3af28a0d}</savedqueryid>
    <layoutxml>
      <grid name="resultset" jump="cmc_staffsurveyquestionname" select="1" preview="1" icon="1">
        <row name="result" id="cmc_staffsurveyquestionid">
          <cell name="cmc_staffsurveyquestionname" width="150" />
          <cell name="createdon" width="100" />
        </row>
      </grid>
    </layoutxml>
    <querytype>0</querytype>
    <fetchxml>
      <fetch version="1.0" output-format="xml-platform" mapping="logical">
        <entity name="cmc_staffsurveyquestion">
          <attribute name="cmc_staffsurveyquestionname" />
          <order attribute="cmc_staffsurveyquestionname" descending="false" />
          <attribute name="createdon" />
          <attribute name="cmc_staffsurveyquestionid" />
        </entity>
      </fetch>
    </fetchxml>
    <IntroducedVersion>1.0</IntroducedVersion>
    <LocalizedNames>
      <LocalizedName description="test" languagecode="1033" />
    </LocalizedNames>
  </savedquery>
</savedqueries>