<?xml version="1.0" encoding="utf-8"?>
<EntityRelationships>
  <EntityRelationship Name="cmc_sourcecategory_contact_sourcecategoryid">
    <EntityRelationshipType>OneToMany</EntityRelationshipType>
    <IsCustomizable>1</IsCustomizable>
    <IntroducedVersion>1.0.0.50</IntroducedVersion>
    <IsHierarchical>0</IsHierarchical>
    <ReferencingEntityName>Contact</ReferencingEntityName>
    <ReferencedEntityName>cmc_sourcecategory</ReferencedEntityName>
    <CascadeAssign>NoCascade</CascadeAssign>
    <CascadeDelete>RemoveLink</CascadeDelete>
    <CascadeReparent>NoCascade</CascadeReparent>
    <CascadeShare>NoCascade</CascadeShare>
    <CascadeUnshare>NoCascade</CascadeUnshare>
    <CascadeRollupView>NoCascade</CascadeRollupView>
    <IsValidForAdvancedFind>1</IsValidForAdvancedFind>
    <ReferencingAttributeName>cmc_sourcecategoryid</ReferencingAttributeName>
    <RelationshipDescription>
      <Descriptions>
        <Description description="Lookup to Source Category" languagecode="1033" />
      </Descriptions>
    </RelationshipDescription>
    <EntityRelationshipRoles>
      <EntityRelationshipRole>
        <NavPaneDisplayOption>UseCollectionName</NavPaneDisplayOption>
        <NavPaneArea>Details</NavPaneArea>
        <NavPaneOrder>10000</NavPaneOrder>
        <NavigationPropertyName>cmc_sourcecategoryid</NavigationPropertyName>
        <CustomLabels>
          <CustomLabel description="" languagecode="1033" />
        </CustomLabels>
        <RelationshipRoleType>1</RelationshipRoleType>
      </EntityRelationshipRole>
      <EntityRelationshipRole>
        <NavigationPropertyName>cmc_sourcecategory_contact_sourcecategoryid</NavigationPropertyName>
        <RelationshipRoleType>0</RelationshipRoleType>
      </EntityRelationshipRole>
    </EntityRelationshipRoles>
  </EntityRelationship>
  <EntityRelationship Name="cmc_sourcecategory_lead_sourcecategoryid">
    <EntityRelationshipType>OneToMany</EntityRelationshipType>
    <IsCustomizable>1</IsCustomizable>
    <IntroducedVersion>1.0.0.50</IntroducedVersion>
    <IsHierarchical>0</IsHierarchical>
    <ReferencingEntityName>Lead</ReferencingEntityName>
    <ReferencedEntityName>cmc_sourcecategory</ReferencedEntityName>
    <CascadeAssign>NoCascade</CascadeAssign>
    <CascadeDelete>RemoveLink</CascadeDelete>
    <CascadeReparent>NoCascade</CascadeReparent>
    <CascadeShare>NoCascade</CascadeShare>
    <CascadeUnshare>NoCascade</CascadeUnshare>
    <CascadeRollupView>NoCascade</CascadeRollupView>
    <IsValidForAdvancedFind>1</IsValidForAdvancedFind>
    <ReferencingAttributeName>cmc_sourcecategoryid</ReferencingAttributeName>
    <RelationshipDescription>
      <Descriptions>
        <Description description="Lookup to Source Category" languagecode="1033" />
      </Descriptions>
    </RelationshipDescription>
    <EntityRelationshipRoles>
      <EntityRelationshipRole>
        <NavPaneDisplayOption>UseCollectionName</NavPaneDisplayOption>
        <NavPaneArea>Details</NavPaneArea>
        <NavPaneOrder>10000</NavPaneOrder>
        <NavigationPropertyName>cmc_sourcecategoryid</NavigationPropertyName>
        <CustomLabels>
          <CustomLabel description="" languagecode="1033" />
        </CustomLabels>
        <RelationshipRoleType>1</RelationshipRoleType>
      </EntityRelationshipRole>
      <EntityRelationshipRole>
        <NavigationPropertyName>cmc_sourcecategory_lead_sourcecategoryid</NavigationPropertyName>
        <RelationshipRoleType>0</RelationshipRoleType>
      </EntityRelationshipRole>
    </EntityRelationshipRoles>
  </EntityRelationship>
  <EntityRelationship Name="cmc_sourcecategory_opportunity_sourcecategoryid">
    <EntityRelationshipType>OneToMany</EntityRelationshipType>
    <IsCustomizable>1</IsCustomizable>
    <IntroducedVersion>1.0.0.56</IntroducedVersion>
    <IsHierarchical>0</IsHierarchical>
    <ReferencingEntityName>Opportunity</ReferencingEntityName>
    <ReferencedEntityName>cmc_sourcecategory</ReferencedEntityName>
    <CascadeAssign>NoCascade</CascadeAssign>
    <CascadeDelete>RemoveLink</CascadeDelete>
    <CascadeReparent>NoCascade</CascadeReparent>
    <CascadeShare>NoCascade</CascadeShare>
    <CascadeUnshare>NoCascade</CascadeUnshare>
    <CascadeRollupView>NoCascade</CascadeRollupView>
    <IsValidForAdvancedFind>1</IsValidForAdvancedFind>
    <ReferencingAttributeName>cmc_sourcecategoryid</ReferencingAttributeName>
    <RelationshipDescription>
      <Descriptions>
        <Description description="Lookup to Source Category." languagecode="1033" />
      </Descriptions>
    </RelationshipDescription>
    <EntityRelationshipRoles>
      <EntityRelationshipRole>
        <NavPaneDisplayOption>UseCollectionName</NavPaneDisplayOption>
        <NavPaneArea>Details</NavPaneArea>
        <NavPaneOrder>10000</NavPaneOrder>
        <NavigationPropertyName>cmc_sourcecategoryid</NavigationPropertyName>
        <CustomLabels>
          <CustomLabel description="" languagecode="1033" />
        </CustomLabels>
        <RelationshipRoleType>1</RelationshipRoleType>
      </EntityRelationshipRole>
      <EntityRelationshipRole>
        <NavigationPropertyName>cmc_sourcecategory_opportunity_sourcecategoryid</NavigationPropertyName>
        <RelationshipRoleType>0</RelationshipRoleType>
      </EntityRelationshipRole>
    </EntityRelationshipRoles>
  </EntityRelationship>
  <EntityRelationship Name="cmc_sourcecategory_sourcesubcategory">
    <EntityRelationshipType>ManyToMany</EntityRelationshipType>
    <IsCustomizable>1</IsCustomizable>
    <IntroducedVersion>1.0.0.51</IntroducedVersion>
    <IsHierarchical>0</IsHierarchical>
    <FirstEntityName>cmc_sourcecategory</FirstEntityName>
    <SecondEntityName>cmc_sourcesubcategory</SecondEntityName>
    <IntersectEntityName>cmc_sourcecategory_sourcesubcategory</IntersectEntityName>
    <IsValidForAdvancedFind>1</IsValidForAdvancedFind>
    <EntityRelationshipRoles>
      <EntityRelationshipRole>
        <NavPaneDisplayOption>UseCollectionName</NavPaneDisplayOption>
        <NavPaneArea>Details</NavPaneArea>
        <NavPaneOrder>10000</NavPaneOrder>
        <NavigationPropertyName>cmc_sourcecategory_sourcesubcategory</NavigationPropertyName>
        <CustomLabels>
          <CustomLabel description="" languagecode="1033" />
        </CustomLabels>
        <AssociationRoleOrdinal>1</AssociationRoleOrdinal>
      </EntityRelationshipRole>
      <EntityRelationshipRole>
        <NavPaneDisplayOption>UseCollectionName</NavPaneDisplayOption>
        <NavPaneArea>Details</NavPaneArea>
        <NavPaneOrder>10000</NavPaneOrder>
        <NavigationPropertyName>cmc_sourcecategory_sourcesubcategory</NavigationPropertyName>
        <CustomLabels>
          <CustomLabel description="" languagecode="1033" />
        </CustomLabels>
        <AssociationRoleOrdinal>2</AssociationRoleOrdinal>
      </EntityRelationshipRole>
    </EntityRelationshipRoles>
  </EntityRelationship>
</EntityRelationships>