<?xml version="1.0" encoding="utf-8"?>
<savedqueries>
  <savedquery>
    <IsCustomizable>1</IsCustomizable>
    <CanBeDeleted>0</CanBeDeleted>
    <isquickfindquery>1</isquickfindquery>
    <isprivate>0</isprivate>
    <isdefault>1</isdefault>
    <savedqueryid>{c8c860eb-490d-4b08-bc82-26c9df7b303d}</savedqueryid>
    <layoutxml>
      <grid name="resultset" jump="cmc_sourcemethodname" select="1" icon="1" preview="1">
        <row name="result" id="cmc_sourcemethodid">
          <cell name="cmc_sourcemethodname" width="300" />
          <cell name="createdon" width="125" />
        </row>
      </grid>
    </layoutxml>
    <querytype>4</querytype>
    <fetchxml>
      <fetch version="1.0" mapping="logical">
        <entity name="cmc_sourcemethod">
          <attribute name="cmc_sourcemethodid" />
          <attribute name="cmc_sourcemethodname" />
          <attribute name="createdon" />
          <order attribute="cmc_sourcemethodname" descending="false" />
          <filter type="and">
            <condition attribute="statecode" operator="eq" value="0" />
          </filter>
          <filter type="or" isquickfindfields="1">
            <condition attribute="cmc_sourcemethodname" operator="like" value="{0}" />
          </filter>
        </entity>
      </fetch>
    </fetchxml>
    <IntroducedVersion>1.0.0.49</IntroducedVersion>
    <LocalizedNames>
      <LocalizedName description="Quick Find Active Source Methods" languagecode="1033" />
    </LocalizedNames>
  </savedquery>
</savedqueries>